Axtrack/__init__.py
Axtrack/grab.py
Axtrack-0.0.1.dist-info/METADATA
Axtrack-0.0.1.dist-info/WHEEL
Axtrack-0.0.1.dist-info/top_level.txt
Axtrack-0.0.1.dist-info/RECORD
